feel_it/__init__.py
feel_it/dataset.py
feel_it/feel_it.py
feel_it-1.0.5.dist-info/AUTHORS.rst
feel_it-1.0.5.dist-info/LICENSE
feel_it-1.0.5.dist-info/METADATA
feel_it-1.0.5.dist-info/WHEEL
feel_it-1.0.5.dist-info/top_level.txt
feel_it-1.0.5.dist-info/RECORD
