Metadata-Version: 2.1
Name: feel-it
Version: 1.0.5
Summary: A python package for sentiment analysis and emotion recognition in italian
Home-page: https://github.com/MilaNLProc/feel-it
Author: Federico Bianchi
Author-email: f.bianchi@unibocconi.it
License: MIT license
Keywords: feel_it
Platform: UNKNOWN
Classifier: Development Status :: 2 - Pre-Alpha
Classifier: Intended Audience :: Developers
Classifier: License :: OSI Approved :: MIT License
Classifier: Natural Language :: English
Classifier: Programming Language :: Python :: 3
Classifier: Programming Language :: Python :: 3.5
Classifier: Programming Language :: Python :: 3.6
Classifier: Programming Language :: Python :: 3.7
Classifier: Programming Language :: Python :: 3.8
Requires-Python: >=3.5
Requires-Dist: transformers (>=4.11.3)
Requires-Dist: numpy
Requires-Dist: torch (>=1.6.0)
